{
	"frames": {
		"background.png": {
			"frame": {
				"x": 1,
				"y": 1,
				"w": 1920,
				"h": 1082
			},
			"rotated": false,
			"trimmed": false,
			"spriteSourceSize": {
				"x": 0,
				"y": 0,
				"w": 1920,
				"h": 1082
			},
			"sourceSize": {
				"w": 1920,
				"h": 1082
			}
		},
		"goomba.gif": {
			"frame": {
				"x": 1,
				"y": 1085,
				"w": 200,
				"h": 200
			},
			"rotated": false,
			"trimmed": false,
			"spriteSourceSize": {
				"x": 0,
				"y": 0,
				"w": 200,
				"h": 200
			},
			"sourceSize": {
				"w": 200,
				"h": 200
			}
		},
		"goomba-base.png": {
			"frame": {
				"x": 203,
				"y": 1085,
				"w": 80,
				"h": 85
			},
			"rotated": false,
			"trimmed": false,
			"spriteSourceSize": {
				"x": 0,
				"y": 0,
				"w": 80,
				"h": 85
			},
			"sourceSize": {
				"w": 80,
				"h": 85
			}
		},
		"goomba-base2.png": {
			"frame": {
				"x": 285,
				"y": 1085,
				"w": 80,
				"h": 85
			},
			"rotated": false,
			"trimmed": false,
			"spriteSourceSize": {
				"x": 0,
				"y": 0,
				"w": 80,
				"h": 85
			},
			"sourceSize": {
				"w": 80,
				"h": 85
			}
		},
		"goomba-droite.png": {
			"frame": {
				"x": 367,
				"y": 1085,
				"w": 80,
				"h": 85
			},
			"rotated": false,
			"trimmed": false,
			"spriteSourceSize": {
				"x": 0,
				"y": 0,
				"w": 80,
				"h": 85
			},
			"sourceSize": {
				"w": 80,
				"h": 85
			}
		},
		"goomba-droite2.png": {
			"frame": {
				"x": 449,
				"y": 1085,
				"w": 80,
				"h": 85
			},
			"rotated": false,
			"trimmed": false,
			"spriteSourceSize": {
				"x": 0,
				"y": 0,
				"w": 80,
				"h": 85
			},
			"sourceSize": {
				"w": 80,
				"h": 85
			}
		},
		"goomba-gauche.png": {
			"frame": {
				"x": 531,
				"y": 1085,
				"w": 80,
				"h": 85
			},
			"rotated": false,
			"trimmed": false,
			"spriteSourceSize": {
				"x": 0,
				"y": 0,
				"w": 80,
				"h": 85
			},
			"sourceSize": {
				"w": 80,
				"h": 85
			}
		},
		"goomba-gauche2.png": {
			"frame": {
				"x": 613,
				"y": 1085,
				"w": 80,
				"h": 85
			},
			"rotated": false,
			"trimmed": false,
			"spriteSourceSize": {
				"x": 0,
				"y": 0,
				"w": 80,
				"h": 85
			},
			"sourceSize": {
				"w": 80,
				"h": 85
			}
		},
		"mario-marche.png": {
			"frame": {
				"x": 695,
				"y": 1085,
				"w": 90,
				"h": 102
			},
			"rotated": false,
			"trimmed": false,
			"spriteSourceSize": {
				"x": 0,
				"y": 0,
				"w": 90,
				"h": 102
			},
			"sourceSize": {
				"w": 90,
				"h": 102
			}
		},
		"mario-run.png": {
			"frame": {
				"x": 787,
				"y": 1085,
				"w": 89,
				"h": 102
			},
			"rotated": false,
			"trimmed": false,
			"spriteSourceSize": {
				"x": 0,
				"y": 0,
				"w": 89,
				"h": 102
			},
			"sourceSize": {
				"w": 89,
				"h": 102
			}
		},
		"mario-w-ombre.png": {
			"frame": {
				"x": 878,
				"y": 1085,
				"w": 70,
				"h": 102
			},
			"rotated": false,
			"trimmed": false,
			"spriteSourceSize": {
				"x": 0,
				"y": 0,
				"w": 70,
				"h": 102
			},
			"sourceSize": {
				"w": 70,
				"h": 102
			}
		},
		"ready.png": {
			"frame": {
				"x": 950,
				"y": 1085,
				"w": 129,
				"h": 53
			},
			"rotated": false,
			"trimmed": false,
			"spriteSourceSize": {
				"x": 0,
				"y": 0,
				"w": 129,
				"h": 53
			},
			"sourceSize": {
				"w": 129,
				"h": 53
			}
		},
		"smb-start-big.png": {
			"frame": {
				"x": 203,
				"y": 1189,
				"w": 1200,
				"h": 601
			},
			"rotated": false,
			"trimmed": false,
			"spriteSourceSize": {
				"x": 0,
				"y": 0,
				"w": 1200,
				"h": 601
			},
			"sourceSize": {
				"w": 1200,
				"h": 601
			}
		},
		"smb-start-normal.png": {
			"frame": {
				"x": 1923,
				"y": 1,
				"w": 600,
				"h": 301
			},
			"rotated": false,
			"trimmed": false,
			"spriteSourceSize": {
				"x": 0,
				"y": 0,
				"w": 600,
				"h": 301
			},
			"sourceSize": {
				"w": 600,
				"h": 301
			}
		},
		"sol-nes.png": {
			"frame": {
				"x": 1,
				"y": 1792,
				"w": 1347,
				"h": 300
			},
			"rotated": false,
			"trimmed": false,
			"spriteSourceSize": {
				"x": 0,
				"y": 0,
				"w": 1347,
				"h": 300
			},
			"sourceSize": {
				"w": 1347,
				"h": 300
			}
		}
	},
	"meta": {
		"app": "http://www.codeandweb.com/texturepacker",
		"version": "1.0",
		"image": "spritesheet.png",
		"format": "RGBA8888",
		"size": {
			"w": 2524,
			"h": 2093
		},
		"scale": "1"
	}
}